<annotation>
	<folder>test</folder>
	<filename>tau_dansu (293).jpg</filename>
	<path>D:\tensorflow\train\images\test\tau_dansu (293).jpg</path>
	<source>
		<database>Unknown</database>
	</source>
	<size>
		<width>276</width>
		<height>183</height>
		<depth>3</depth>
	</size>
	<segmented>0</segmented>
	<object>
		<name>tau_dansu</name>
		<pose>Unspecified</pose>
		<truncated>0</truncated>
		<difficult>0</difficult>
		<bndbox>
			<xmin>85</xmin>
			<ymin>138</ymin>
			<xmax>172</xmax>
			<ymax>167</ymax>
		</bndbox>
	</object>
	<object>
		<name>tau_dansu</name>
		<pose>Unspecified</pose>
		<truncated>0</truncated>
		<difficult>0</difficult>
		<bndbox>
			<xmin>168</xmin>
			<ymin>134</ymin>
			<xmax>205</xmax>
			<ymax>168</ymax>
		</bndbox>
	</object>
	<object>
		<name>tau_dansu</name>
		<pose>Unspecified</pose>
		<truncated>0</truncated>
		<difficult>0</difficult>
		<bndbox>
			<xmin>203</xmin>
			<ymin>136</ymin>
			<xmax>245</xmax>
			<ymax>168</ymax>
		</bndbox>
	</object>
	<object>
		<name>tau_dansu</name>
		<pose>Unspecified</pose>
		<truncated>0</truncated>
		<difficult>0</difficult>
		<bndbox>
			<xmin>33</xmin>
			<ymin>139</ymin>
			<xmax>63</xmax>
			<ymax>151</ymax>
		</bndbox>
	</object>
	<object>
		<name>tau_dansu</name>
		<pose>Unspecified</pose>
		<truncated>0</truncated>
		<difficult>0</difficult>
		<bndbox>
			<xmin>14</xmin>
			<ymin>136</ymin>
			<xmax>36</xmax>
			<ymax>149</ymax>
		</bndbox>
	</object>
</annotation>
